CHANGES.rst
MANIFEST.in
README.rst
setup.py
bin/activate_this.py
buildout_script/__init__.py
buildout_script/script.py
buildout_script/template.py
buildout_script.egg-info/PKG-INFO
buildout_script.egg-info/SOURCES.txt
buildout_script.egg-info/dependency_links.txt
buildout_script.egg-info/entry_points.txt
buildout_script.egg-info/requires.txt
buildout_script.egg-info/top_level.txt
buildout_script.egg-info/zip-safe
buildout_script/templates/paster-check.sh.in
lib/python2.7/UserDict.py
lib/python2.7/_abcoll.py
lib/python2.7/_weakrefset.py
lib/python2.7/abc.py
lib/python2.7/codecs.py
lib/python2.7/copy_reg.py
lib/python2.7/fnmatch.py
lib/python2.7/genericpath.py
lib/python2.7/linecache.py
lib/python2.7/locale.py
lib/python2.7/ntpath.py
lib/python2.7/os.py
lib/python2.7/posixpath.py
lib/python2.7/re.py
lib/python2.7/site.py
lib/python2.7/sre.py
lib/python2.7/sre_compile.py
lib/python2.7/sre_constants.py
lib/python2.7/sre_parse.py
lib/python2.7/stat.py
lib/python2.7/types.py
lib/python2.7/warnings.py
lib/python2.7/config/config.c.in
lib/python2.7/distutils/__init__.py
lib/python2.7/encodings/__init__.py
lib/python2.7/encodings/aliases.py
lib/python2.7/encodings/ascii.py
lib/python2.7/encodings/base64_codec.py
lib/python2.7/encodings/big5.py
lib/python2.7/encodings/big5hkscs.py
lib/python2.7/encodings/bz2_codec.py
lib/python2.7/encodings/charmap.py
lib/python2.7/encodings/cp037.py
lib/python2.7/encodings/cp1006.py
lib/python2.7/encodings/cp1026.py
lib/python2.7/encodings/cp1140.py
lib/python2.7/encodings/cp1250.py
lib/python2.7/encodings/cp1251.py
lib/python2.7/encodings/cp1252.py
lib/python2.7/encodings/cp1253.py
lib/python2.7/encodings/cp1254.py
lib/python2.7/encodings/cp1255.py
lib/python2.7/encodings/cp1256.py
lib/python2.7/encodings/cp1257.py
lib/python2.7/encodings/cp1258.py
lib/python2.7/encodings/cp424.py
lib/python2.7/encodings/cp437.py
lib/python2.7/encodings/cp500.py
lib/python2.7/encodings/cp720.py
lib/python2.7/encodings/cp737.py
lib/python2.7/encodings/cp775.py
lib/python2.7/encodings/cp850.py
lib/python2.7/encodings/cp852.py
lib/python2.7/encodings/cp855.py
lib/python2.7/encodings/cp856.py
lib/python2.7/encodings/cp857.py
lib/python2.7/encodings/cp858.py
lib/python2.7/encodings/cp860.py
lib/python2.7/encodings/cp861.py
