Metadata-Version: 1.1
Name: buildout-script
Version: 0.3.1
Summary: zc.buildout recipes for generating script and conf files from templates.
Home-page: https://github.com/nyergler/buildout_script
Author: Nathan R. Yergler
Author-email: nathan@yergler.net
License: MIT License
Platform: UNKNOWN
Classifier: Framework :: Buildout
Classifier: Development Status :: 4 - Beta
Classifier: Intended Audience :: Developers
Classifier: License :: OSI Approved :: MIT License
Classifier: Topic :: Software Development :: Build Tools
Classifier: Topic :: Software Development :: Libraries :: Python Modules
